azure/mgmt/batchai/__init__.py
azure/mgmt/batchai/_batch_ai.py
azure/mgmt/batchai/_configuration.py
azure/mgmt/batchai/_version.py
azure/mgmt/batchai/py.typed
azure/mgmt/batchai/aio/__init__.py
azure/mgmt/batchai/aio/_batch_ai.py
azure/mgmt/batchai/aio/_configuration.py
azure/mgmt/batchai/aio/operations/__init__.py
azure/mgmt/batchai/aio/operations/_clusters_operations.py
azure/mgmt/batchai/aio/operations/_experiments_operations.py
azure/mgmt/batchai/aio/operations/_file_servers_operations.py
azure/mgmt/batchai/aio/operations/_jobs_operations.py
azure/mgmt/batchai/aio/operations/_operations.py
azure/mgmt/batchai/aio/operations/_usages_operations.py
azure/mgmt/batchai/aio/operations/_workspaces_operations.py
azure/mgmt/batchai/models/__init__.py
azure/mgmt/batchai/models/_batch_ai_enums.py
azure/mgmt/batchai/models/_models.py
azure/mgmt/batchai/models/_models_py3.py
azure/mgmt/batchai/operations/__init__.py
azure/mgmt/batchai/operations/_clusters_operations.py
azure/mgmt/batchai/operations/_experiments_operations.py
azure/mgmt/batchai/operations/_file_servers_operations.py
azure/mgmt/batchai/operations/_jobs_operations.py
azure/mgmt/batchai/operations/_operations.py
azure/mgmt/batchai/operations/_usages_operations.py
azure/mgmt/batchai/operations/_workspaces_operations.py
azure_mgmt_batchai-7.0.0.dist-info/LICENSE
azure_mgmt_batchai-7.0.0.dist-info/METADATA
azure_mgmt_batchai-7.0.0.dist-info/WHEEL
azure_mgmt_batchai-7.0.0.dist-info/top_level.txt
azure_mgmt_batchai-7.0.0.dist-info/RECORD
